[
  {
    "kind": "class",
    "name": "AFGEquipmentStunSpear",
    "category": "UCLASS",
    "comment": "Copyright 2016-2018 Coffee Stain Studios. All Rights Reserved.",
    "extends": [
      "AFGEquipment"
    ],
    "methods": [
      {
        "name": "AFGEquipmentStunSpear"
      },
      {
        "name": "AddEquipmentActionBindings",
        "comment": "Add custom bindings for this equipment",
        "returnType": "void"
      },
      {
        "name": "PlayStunEffects",
        "comment": "Called when the player clicks to \"fire\"",
        "returnType": "void"
      },
      {
        "name": "GetShouldPlaySecondSwing",
        "comment": "Getter for mShouldPlaySecondSwing",
        "returnType": "bool"
      },
      {
        "name": "DoAttack",
        "comment": "Start the damage chain",
        "returnType": "void"
      },
      {
        "name": "OnHitTarget",
        "returnType": "void"
      },
      {
        "name": "Server_ShockEnemy",
        "comment": "server notified of hit from client to verify",
        "returnType": "void"
      },
      {
        "name": "OnFirePressed",
        "comment": "Key binded functions",
        "returnType": "void"
      }
    ],
    "properties": [
      {
        "name": "mCollisionComp",
        "comment": "Sphere collision component",
        "type": "classUSphereComponent*"
      },
      {
        "name": "mDamageTypeClass",
        "comment": "Damage type to use when hitting others",
        "type": "TSubclassOf<classUFGDamageType>"
      },
      {
        "name": "mFirstSwingTime",
        "comment": "Timer started",
        "type": "float"
      },
      {
        "name": "mSecondSwingMaxTime",
        "comment": "The max amount of time between the first swing that will still trigger the second swing",
        "type": "float"
      },
      {
        "name": "mShouldPlaySecondSwing",
        "comment": "Indicates if we should do the second swing",
        "type": "bool"
      },
      {
        "name": "mCoolDown",
        "comment": "Timestamp when cooldown began",
        "type": "float"
      },
      {
        "name": "mSecondSwingCooldDownTime",
        "comment": "The max amount of time between the first swing that will still trigger the second swing",
        "type": "float"
      },
      {
        "name": "mDamage",
        "comment": "Damage amount",
        "type": "int32"
      },
      {
        "name": "mAttackDistance",
        "comment": "How much inf ront of character the attack is",
        "type": "float"
      }
    ]
  }
]