[
  {
    "kind": "class",
    "name": "AFGProfileSpline",
    "category": "UCLASS",
    "comment": "Copyright 2016-2019 Coffee Stain Studios. All Rights Reserved.",
    "extends": [
      "AActor"
    ],
    "methods": [
      {
        "name": "AFGProfileSpline",
        "comment": "Sets default values for this actor's properties"
      },
      {
        "name": "BeginPlay",
        "comment": "Called when the game starts or when spawned",
        "returnType": "void"
      },
      {
        "name": "Tick",
        "comment": "Called every frame",
        "returnType": "void"
      },
      {
        "name": "StartProfile",
        "returnType": "void"
      }
    ],
    "properties": [
      {
        "name": "Duration",
        "comment": "Runtime length of the spline in minutes.",
        "type": "float"
      }
    ]
  }
]