[
  {
    "kind": "class",
    "name": "FSaveCollectorArchive",
    "extends": [
      "FArchive"
    ],
    "methods": [
      {
        "name": "operator<<",
        "comment": "Handles serialization of UObject references",
        "returnType": "FArchive&"
      },
      {
        "name": "FSaveCollectorArchive",
        "comment": "Sets up the array that we want to add objects to\n"
      },
      {
        "name": "GenerateSaveObjects",
        "comment": "Generates objects to the member that was passed in when class was setup",
        "returnType": "void"
      }
    ],
    "properties": [
      {
        "name": "mObjectsToSave",
        "comment": "The set of objects encountered when traversing the object graph",
        "type": "TArray<classUObject*>&"
      }
    ]
  }
]